highbond_sdk/__init__.py
highbond_sdk/client.py
highbond_sdk/config.py
highbond_sdk/enums.py
highbond_sdk/exceptions.py
highbond_sdk/http_client.py
highbond_sdk/utils.py
highbond_sdk/modules/__init__.py
highbond_sdk/modules/controls.py
highbond_sdk/modules/issues.py
highbond_sdk/modules/objectives.py
highbond_sdk/modules/project_types.py
highbond_sdk/modules/projects.py
highbond_sdk/modules/risks.py
highbond_sdk-0.0.9.dist-info/licenses/LICENSE
highbond_sdk-0.0.9.dist-info/METADATA
highbond_sdk-0.0.9.dist-info/WHEEL
highbond_sdk-0.0.9.dist-info/top_level.txt
highbond_sdk-0.0.9.dist-info/RECORD
